compositefk/__init__.py
compositefk/compat.py
compositefk/fields.py
compositefk/related_descriptors.py
django_composite_foreignkey_2-3.9.0.dist-info/LICENSE
django_composite_foreignkey_2-3.9.0.dist-info/METADATA
django_composite_foreignkey_2-3.9.0.dist-info/WHEEL
django_composite_foreignkey_2-3.9.0.dist-info/top_level.txt
django_composite_foreignkey_2-3.9.0.dist-info/RECORD
