Metadata-Version: 2.1
Name: django-composite-foreignkey-2
Version: 3.9.0
Summary: composite foreignkey support for Django 4.x
Home-page: https://github.com/darkpixel/django-composite-foreignkey
Author: Darius BERNARD
Author-email: contact@xornot.fr
License: GNU GENERAL PUBLIC LICENSE
Keywords: django composite foreignkey
Platform: UNKNOWN
Classifier: Development Status :: 4 - Beta
Classifier: Intended Audience :: Developers
Classifier: License :: OSI Approved :: GNU General Public License v3 (GPLv3)
Classifier: Programming Language :: Python :: 3
Classifier: Programming Language :: Python :: 3.4
Classifier: Programming Language :: Python :: 3.5
Classifier: Programming Language :: Python :: 3.6
Classifier: Programming Language :: Python :: 3.7
Classifier: Programming Language :: Python :: 3.8
Classifier: Programming Language :: Python :: 3.9
Classifier: Operating System :: OS Independent
Classifier: Topic :: Software Development :: Libraries
Classifier: Topic :: Utilities
Classifier: Environment :: Web Environment
Classifier: Framework :: Django :: 4.0
License-File: LICENSE
